[{"name":"ACE_M113A3_Ambul","displayname":"M113A3 (MEDEVAC)","faction":"BIS_US","weapons":[{"name":"SmokeLauncher"}],"magazines":[{"name":"SmokeLauncherMag"}],"turrets":[]},{"name":"ACE_Truck5tReammo","displayname":"M923A2 (Ammunition)","faction":"BIS_US","weapons":[{"name":"TruckHorn"}],"magazines":[],"turrets":[]},{"name":"ACE_Truck5tRefuel","displayname":"M923A2 (fuel)","faction":"BIS_US","weapons":[{"name":"TruckHorn"}],"magazines":[],"turrets":[]},{"name":"ACE_Truck5tRepair","displayname":"M923A2 (repair)","faction":"BIS_US","weapons":[{"name":"TruckHorn"}],"magazines":[],"turrets":[]},{"name":"ACE_UralReammo_RU","displayname":"Ural (ammo)","faction":"RU","weapons":[{"name":"TruckHorn"}],"magazines":[],"turrets":[]},{"name":"ACE_UralRefuel_RU","displayname":"Ural (fuel)","faction":"RU","weapons":[{"name":"TruckHorn"}],"magazines":[],"turrets":[]},{"name":"ACE_UralRepair_RU","displayname":"Ural (repair)","faction":"RU","weapons":[{"name":"TruckHorn"}],"magazines":[],"turrets":[]},{"name":"BMP2_Ambul_CDF","displayname":"BVP-2 (MEDEVAC)","faction":"CDF","weapons":[],"magazines":[],"turrets":[]},{"name":"BMP2_Ambul_INS","displayname":"BMP-2 (MEDEVAC)","faction":"INS","weapons":[],"magazines":[],"turrets":[]},{"name":"GAZ_Vodnik_MedEvac","displayname":"GAZ Vodnik (MEDEVAC)","faction":"RU","weapons":[{"name":"TruckHorn2"}],"magazines":[],"turrets":[]},{"name":"HMMWV_Ambulance","displayname":"M997 HMMWV (MEDEVAC)","faction":"USMC","weapons":[{"name":"CarHorn"}],"magazines":[],"turrets":[]},{"name":"HMMWV_Ambulance_CZ_DES_EP1","displayname":"M997 HMMWV (MEDEVAC)","faction":"BIS_CZ","weapons":[{"name":"CarHorn"}],"magazines":[],"turrets":[]},{"name":"HMMWV_Ambulance_DES_EP1","displayname":"M997 HMMWV (MEDEVAC)","faction":"BIS_US","weapons":[{"name":"CarHorn"}],"magazines":[],"turrets":[]},{"name":"KamazReammo","displayname":"KAMAZ (ammo)","faction":"RU","weapons":[{"name":"TruckHorn"}],"magazines":[],"turrets":[]},{"name":"KamazRefuel","displayname":"KAMAZ (fuel)","faction":"RU","weapons":[{"name":"TruckHorn"}],"magazines":[],"turrets":[]},{"name":"KamazRepair","displayname":"KAMAZ (repair)","faction":"RU","weapons":[{"name":"TruckHorn"}],"magazines":[],"turrets":[]},{"name":"M1133_MEV_EP1","displayname":"M1133 Stryker MEV","faction":"BIS_US","weapons":[],"magazines":[],"turrets":[]},{"name":"M113Ambul_TK_EP1","displayname":"M113A3 (MEDEVAC)","faction":"BIS_TK","weapons":[{"name":"SmokeLauncher"}],"magazines":[{"name":"SmokeLauncherMag"}],"turrets":[]},{"name":"M113Ambul_UN_EP1","displayname":"M113A3 (MEDEVAC)","faction":"BIS_UN","weapons":[{"name":"SmokeLauncher"}],"magazines":[{"name":"SmokeLauncherMag"}],"turrets":[]},{"name":"Mi17_medevac_CDF","displayname":"Mi-17-1VA (MEDEVAC)","faction":"CDF","weapons":[],"magazines":[],"turrets":[]},{"name":"Mi17_medevac_Ins","displayname":"Mi-8MT (MEDEVAC)","faction":"INS","weapons":[],"magazines":[],"turrets":[]},{"name":"Mi17_medevac_RU","displayname":"Mi-8MT (MEDEVAC)","faction":"RU","weapons":[],"magazines":[],"turrets":[]},{"name":"MtvrReammo","displayname":"MTVR (ammo)","faction":"USMC","weapons":[{"name":"TruckHorn"}],"magazines":[],"turrets":[]},{"name":"MtvrReammo_DES_EP1","displayname":"MTVR (Ammunition)","faction":"BIS_US","weapons":[{"name":"TruckHorn"}],"magazines":[],"turrets":[]},{"name":"MtvrRefuel","displayname":"MTVR (fuel)","faction":"USMC","weapons":[{"name":"TruckHorn"}],"magazines":[],"turrets":[]},{"name":"MtvrRefuel_DES_EP1","displayname":"MTVR (Fuel)","faction":"BIS_US","weapons":[{"name":"TruckHorn"}],"magazines":[],"turrets":[]},{"name":"MtvrRepair","displayname":"MTVR (repair)","faction":"USMC","weapons":[{"name":"TruckHorn"}],"magazines":[],"turrets":[]},{"name":"MtvrRepair_DES_EP1","displayname":"MTVR (Repair)","faction":"BIS_US","weapons":[{"name":"TruckHorn"}],"magazines":[],"turrets":[]},{"name":"MtvrSalvage_DES_EP1","displayname":"Salvage Truck","faction":"BIS_US","weapons":[{"name":"TruckHorn"}],"magazines":[],"turrets":[]},{"name":"MtvrSupply_DES_EP1","displayname":"Supply Truck","faction":"BIS_US","weapons":[{"name":"TruckHorn"}],"magazines":[],"turrets":[]},{"name":"S1203_ambulance_EP1","displayname":"Å koda (ambulance)","faction":"BIS_TK_CIV","weapons":[{"name":"CarHorn"}],"magazines":[],"turrets":[]},{"name":"UH60M_MEV_EP1","displayname":"UH-60M (MEDEVAC)","faction":"BIS_US","weapons":[{"name":"CMFlareLauncher"}],"magazines":[{"name":"60Rnd_CMFlareMagazine"}],"turrets":[]},{"name":"UralReammo_CDF","displayname":"Ural (ammo)","faction":"CDF","weapons":[{"name":"TruckHorn"}],"magazines":[],"turrets":[]},{"name":"UralReammo_INS","displayname":"Ural (ammo)","faction":"INS","weapons":[{"name":"TruckHorn"}],"magazines":[],"turrets":[]},{"name":"UralReammo_TK_EP1","displayname":"Ural (ammo)","faction":"BIS_TK","weapons":[{"name":"TruckHorn"}],"magazines":[],"turrets":[]},{"name":"UralRefuel_CDF","displayname":"Ural (fuel)","faction":"CDF","weapons":[{"name":"TruckHorn"}],"magazines":[],"turrets":[]},{"name":"UralRefuel_INS","displayname":"Ural (fuel)","faction":"INS","weapons":[{"name":"TruckHorn"}],"magazines":[],"turrets":[]},{"name":"UralRefuel_TK_EP1","displayname":"Ural (fuel)","faction":"BIS_TK","weapons":[{"name":"TruckHorn"}],"magazines":[],"turrets":[]},{"name":"UralRepair_CDF","displayname":"Ural (repair)","faction":"CDF","weapons":[{"name":"TruckHorn"}],"magazines":[],"turrets":[]},{"name":"UralRepair_INS","displayname":"Ural (repair)","faction":"INS","weapons":[{"name":"TruckHorn"}],"magazines":[],"turrets":[]},{"name":"UralRepair_TK_EP1","displayname":"Ural (repair)","faction":"BIS_TK","weapons":[{"name":"TruckHorn"}],"magazines":[],"turrets":[]},{"name":"UralSalvage_TK_EP1","displayname":"Salvage Truck","faction":"BIS_TK","weapons":[{"name":"TruckHorn"}],"magazines":[],"turrets":[]},{"name":"UralSupply_TK_EP1","displayname":"Supply Truck","faction":"BIS_TK","weapons":[{"name":"TruckHorn"}],"magazines":[],"turrets":[]},{"name":"V3S_Reammo_TK_GUE_EP1","displayname":"Praga (ammo)","faction":"BIS_TK_GUE","weapons":[{"name":"TruckHorn"}],"magazines":[],"turrets":[]},{"name":"V3S_Refuel_TK_GUE_EP1","displayname":"Praga (fuel)","faction":"BIS_TK_GUE","weapons":[{"name":"TruckHorn"}],"magazines":[],"turrets":[]},{"name":"V3S_Repair_TK_GUE_EP1","displayname":"Praga (repair)","faction":"BIS_TK_GUE","weapons":[{"name":"TruckHorn"}],"magazines":[],"turrets":[]},{"name":"V3S_Salvage_TK_GUE_EP1","displayname":"Salvage Truck","faction":"BIS_TK_GUE","weapons":[{"name":"TruckHorn"}],"magazines":[],"turrets":[]},{"name":"V3S_Supply_TK_GUE_EP1","displayname":"Supply Truck","faction":"BIS_TK_GUE","weapons":[{"name":"TruckHorn"}],"magazines":[],"turrets":[]}]